AUTHORS
ChangeLog
LICENSE
README.rst
TODO.md
haproxystats-architecture.png
haproxystats.conf
requirements.txt
setup.cfg
setup.py
contrib/tcp_server.py
contrib/ansible-playbook/hosts
contrib/ansible-playbook/main-playbook.yml
contrib/ansible-playbook/group_vars/all
contrib/ansible-playbook/roles/create-newuser/tasks/main.yml
contrib/ansible-playbook/roles/haproxy-socket-dir-permission/tasks/main.yml
contrib/ansible-playbook/roles/haproxystats-config-file/tasks/main.yml
contrib/ansible-playbook/roles/haproxystats-config-file/templates/haproxystats.conf.j2
contrib/ansible-playbook/roles/install-dependency-package/tasks/main.yml
contrib/ansible-playbook/roles/install-haproxystats/tasks/main.yml
contrib/ansible-playbook/roles/systemd-files/tasks/main.yml
contrib/ansible-playbook/roles/systemd-files/templates/haproxystats-process.service.j2
contrib/ansible-playbook/roles/systemd-files/templates/haproxystats-pull.service.j2
contrib/nagios/check_haproxystats_process.sh
contrib/nagios/check_haproxystats_process_number_of_procs.sh
contrib/nagios/check_haproxystats_pull.sh
contrib/nagios/check_haproxystats_queue_size.py
contrib/puppet/manifests/init.pp
contrib/puppet/manifests/params.pp
contrib/puppet/templates/defaults.conf.erb
contrib/puppet/templates/exclude_backend.conf.erb
contrib/puppet/templates/exclude_frontend.conf.erb
contrib/puppet/templates/haproxystats-process-monit-check.sh.erb
contrib/puppet/templates/process-systemd-overwrites.conf.erb
contrib/puppet/templates/process.conf.erb
contrib/puppet/templates/pull-systemd-overwrites.conf.erb
contrib/puppet/templates/pull.conf.erb
contrib/systemd/haproxystats-process.service
contrib/systemd/haproxystats-pull.service
haproxystats/__init__.py
haproxystats/metrics.py
haproxystats/process.py
haproxystats/pull.py
haproxystats/utils.py
haproxystats.egg-info/PKG-INFO
haproxystats.egg-info/SOURCES.txt
haproxystats.egg-info/dependency_links.txt
haproxystats.egg-info/entry_points.txt
haproxystats.egg-info/not-zip-safe
haproxystats.egg-info/pbr.json
haproxystats.egg-info/requires.txt
haproxystats.egg-info/top_level.txt