Metadata-Version: 1.2
Name: haproxystats
Version: 0.5.1
Summary: A HAProxy statistics collection program
Home-page: https://github.com/unixsurfer/haproxystats
Author: Pavlos Parissis
Author-email: pavlos.parissis@gmail.com
Maintainer: Pavlos Parissis
Maintainer-email: pavlos.parissis@gmail.com
License: Apache 2.0
Keywords: haproxystats haproxy stats collector statistics
Platform: UNKNOWN
Classifier: Development Status :: 5 - Production/Stable
Classifier: Environment :: Console
Classifier: Intended Audience :: Information Technology
Classifier: Intended Audience :: System Administrators
Classifier: Natural Language :: English
Classifier: Operating System :: POSIX
Classifier: Programming Language :: Python :: 3.4
Classifier: Topic :: Utilities
